bluesky_darkframes/__init__.py
bluesky_darkframes/_version.py
bluesky_darkframes/sim.py
bluesky_darkframes/tests/__init__.py
bluesky_darkframes/tests/conftest.py
bluesky_darkframes/tests/tests.py
bluesky_darkframes-0.6.0.dist-info/AUTHORS.rst
bluesky_darkframes-0.6.0.dist-info/LICENSE
bluesky_darkframes-0.6.0.dist-info/METADATA
bluesky_darkframes-0.6.0.dist-info/WHEEL
bluesky_darkframes-0.6.0.dist-info/top_level.txt
bluesky_darkframes-0.6.0.dist-info/RECORD
