Metadata-Version: 2.1
Name: bluesky-darkframes
Version: 0.6.0
Summary: Tools for acquiring and subtracting darkframes
Home-page: https://github.com/bluesky/bluesky-darkframes
Author: Brookhaven National Lab
Author-email: dallan@bnl.gov
License: BSD (3-clause)
Classifier: Development Status :: 2 - Pre-Alpha
Classifier: Natural Language :: English
Classifier: Programming Language :: Python :: 3
Requires-Python: >=3.8
License-File: LICENSE
License-File: AUTHORS.rst
Requires-Dist: bluesky
Requires-Dist: event-model (>=1.14.0)
Requires-Dist: frozendict
Requires-Dist: numpy
